pydin/__init__.py
pydin/api.py
pydin/cache.py
pydin/cli.py
pydin/config.py
pydin/const.py
pydin/core.py
pydin/db.py
pydin/fields.py
pydin/logger.py
pydin/models.py
pydin/sources.py
pydin/utils.py
pydin/web.py
pydin/wrap.py
pydin/demo/cli.txt
pydin/demo/web.txt
pydin/samples/gitignore.txt
pydin/samples/head.txt
pydin/samples/job.txt
pydin/samples/scheduler.txt
pydin/samples/script.txt
pydin-0.2.0.dist-info/LICENSE
pydin-0.2.0.dist-info/METADATA
pydin-0.2.0.dist-info/WHEEL
pydin-0.2.0.dist-info/top_level.txt
pydin-0.2.0.dist-info/RECORD
