Metadata-Version: 2.1
Name: pydin
Version: 0.2.0
Summary: Python ETL framework.
Home-page: https://github.com/t3eHawk/pydin
Author: Timur Faradzhov
Author-email: timurfaradzhov@gmail.com
License: MIT
Classifier: Programming Language :: Python :: 3.7
Classifier: Programming Language :: Python :: 3.11
Classifier: License :: OSI Approved :: MIT License
Classifier: Operating System :: OS Independent
Requires-Python: >=3.7
License-File: LICENSE
Requires-Dist: pepperoni (==0.2.1)
Requires-Dist: SQLAlchemy (==1.4.46)
Requires-Dist: cx-Oracle (==8.3.0)
Requires-Dist: paramiko (==3.0.0)
Requires-Dist: Flask (==2.2.2)
Requires-Dist: Flask-HTTPAuth (==4.7.0)
Requires-Dist: waitress (==2.1.2)
Requires-Dist: sqlparse (==0.4.3)
Requires-Dist: GitPython (==3.1.30)
